mcga/__init__.py
mcga/core.py
mcga/detection.py
tests/__init__.py
tests/conftest.py
tests/test_core.py
tests/test_detection.py
tests/test_performance.py
mcga-1.4.5.dist-info/METADATA
mcga-1.4.5.dist-info/WHEEL
mcga-1.4.5.dist-info/entry_points.txt
mcga-1.4.5.dist-info/top_level.txt
mcga-1.4.5.dist-info/RECORD
