Metadata-Version: 2.4
Name: mcga
Version: 1.4.5
Summary: Make Chickening Great Again - TREMENDOUS tariffs with chicken-out behavior!
Author: oha
Author-email: aaronoh2015@gmail.com
Project-URL: Bug Reports, https://github.com/duriantaco/mcga/issues
Project-URL: Source, https://github.com/duriantaco/mcga
Classifier: Development Status :: 5 - Production/Stable
Classifier: Intended Audience :: Developers
Classifier: License :: OSI Approved :: MIT License
Classifier: Programming Language :: Python :: 3
Classifier: Programming Language :: Python :: 3.9
Classifier: Programming Language :: Python :: 3.10
Classifier: Programming Language :: Python :: 3.11
Classifier: Programming Language :: Python :: 3.12
Classifier: Topic :: Software Development :: Libraries :: Python Modules
Classifier: Topic :: Utilities
Requires-Python: >=3.9
Dynamic: author
Dynamic: author-email
Dynamic: classifier
Dynamic: description
Dynamic: project-url
Dynamic: requires-python
Dynamic: summary
